milkid/__init__.py
milkid/core.py
milkid-0.1.1.dist-info/METADATA
milkid-0.1.1.dist-info/WHEEL
milkid-0.1.1.dist-info/RECORD
