Metadata-Version: 2.1
Name: milkid
Version: 0.1.1
Summary: milkid for python
Home-page: https://github.com/kawaiior/milkid-for-python
Author: kawaiior
Author-email: kawaiiorv@gmail.com
Requires-Python: >=3.8,<4.0
Classifier: Programming Language :: Python :: 3
Classifier: Programming Language :: Python :: 3.8
Classifier: Programming Language :: Python :: 3.9
Classifier: Programming Language :: Python :: 3.10
Classifier: Programming Language :: Python :: 3.11
Classifier: Programming Language :: Python :: 3.12
Classifier: Programming Language :: Python :: 3.13
Requires-Dist: xxhash (>=3.0.0,<4.0.0)
Project-URL: Repository, https://github.com/kawaiior/milkid-for-python
